Metadata-Version: 2.4
Name: talon-one-sdk
Version: 26.1
Summary: Talon.One API
Home-page: https://github.com/talon-one/talon-one-python-sdk/
Author: Talon.One GmbH
Author-email: OpenAPI Generator Community <team@openapitools.org>
Project-URL: Repository, https://github.com/talon-one/talon-one-python-sdk
Keywords: OpenAPI,OpenAPI-Generator,Talon.One API
Requires-Python: >=3.9
Requires-Dist: urllib3<3.0.0,>=2.1.0
Requires-Dist: python-dateutil>=2.8.2
Requires-Dist: pydantic>=2
Requires-Dist: typing-extensions>=4.7.1
Dynamic: author
Dynamic: home-page
